{
    "coordinates": [
        {
            "latitude": 36.758418,
            "longitude": 127.977417
        },
        {
            "latitude": 36.758372,
            "longitude": 127.977523
        },
        {
            "latitude": 36.758242,
            "longitude": 127.977605
        },
        {
            "latitude": 36.758115,
            "longitude": 127.977673
        },
        {
            "latitude": 36.757962,
            "longitude": 127.977595
        },
        {
            "latitude": 36.757825,
            "longitude": 127.97754
        },
        {
            "latitude": 36.757725,
            "longitude": 127.977508
        },
        {
            "latitude": 36.757585,
            "longitude": 127.977373
        },
        {
            "latitude": 36.757425,
            "longitude": 127.977315
        },
        {
            "latitude": 36.757277,
            "longitude": 127.977282
        },
        {
            "latitude": 36.757207,
            "longitude": 127.977195
        },
        {
            "latitude": 36.757143,
            "longitude": 127.977108
        },
        {
            "latitude": 36.756992,
            "longitude": 127.977058
        },
        {
            "latitude": 36.75692,
            "longitude": 127.976987
        },
        {
            "latitude": 36.756808,
            "longitude": 127.976927
        },
        {
            "latitude": 36.756663,
            "longitude": 127.976883
        },
        {
            "latitude": 36.756557,
            "longitude": 127.976883
        },
        {
            "latitude": 36.756535,
            "longitude": 127.976912
        },
        {
            "latitude": 36.756443,
            "longitude": 127.976883
        },
        {
            "latitude": 36.756307,
            "longitude": 127.97691
        },
        {
            "latitude": 36.756217,
            "longitude": 127.976958
        },
        {
            "latitude": 36.756132,
            "longitude": 127.97707
        },
        {
            "latitude": 36.756077,
            "longitude": 127.977247
        },
        {
            "latitude": 36.755913,
            "longitude": 127.977168
        },
        {
            "latitude": 36.755925,
            "longitude": 127.977055
        },
        {
            "latitude": 36.755885,
            "longitude": 127.976945
        },
        {
            "latitude": 36.75585,
            "longitude": 127.976835
        },
        {
            "latitude": 36.755825,
            "longitude": 127.976675
        },
        {
            "latitude": 36.755788,
            "longitude": 127.976553
        },
        {
            "latitude": 36.755727,
            "longitude": 127.976425
        },
        {
            "latitude": 36.755698,
            "longitude": 127.97628
        },
        {
            "latitude": 36.755777,
            "longitude": 127.976122
        },
        {
            "latitude": 36.755902,
            "longitude": 127.976027
        },
        {
            "latitude": 36.755948,
            "longitude": 127.975888
        },
        {
            "latitude": 36.75588,
            "longitude": 127.975667
        },
        {
            "latitude": 36.755832,
            "longitude": 127.975565
        },
        {
            "latitude": 36.755765,
            "longitude": 127.975485
        },
        {
            "latitude": 36.755657,
            "longitude": 127.97539
        },
        {
            "latitude": 36.75558,
            "longitude": 127.975305
        },
        {
            "latitude": 36.7555,
            "longitude": 127.97523
        },
        {
            "latitude": 36.755408,
            "longitude": 127.975137
        },
        {
            "latitude": 36.755313,
            "longitude": 127.975087
        },
        {
            "latitude": 36.755118,
            "longitude": 127.975013
        },
        {
            "latitude": 36.755005,
            "longitude": 127.975017
        },
        {
            "latitude": 36.754917,
            "longitude": 127.975025
        },
        {
            "latitude": 36.754815,
            "longitude": 127.97503
        },
        {
            "latitude": 36.754695,
            "longitude": 127.975047
        },
        {
            "latitude": 36.754563,
            "longitude": 127.975097
        },
        {
            "latitude": 36.75446,
            "longitude": 127.975115
        },
        {
            "latitude": 36.754363,
            "longitude": 127.975185
        },
        {
            "latitude": 36.754327,
            "longitude": 127.975302
        },
        {
            "latitude": 36.754322,
            "longitude": 127.975423
        },
        {
            "latitude": 36.754378,
            "longitude": 127.975505
        },
        {
            "latitude": 36.754383,
            "longitude": 127.975628
        },
        {
            "latitude": 36.754328,
            "longitude": 127.975758
        },
        {
            "latitude": 36.75423,
            "longitude": 127.97579
        },
        {
            "latitude": 36.754117,
            "longitude": 127.975745
        },
        {
            "latitude": 36.754035,
            "longitude": 127.975672
        },
        {
            "latitude": 36.753937,
            "longitude": 127.975722
        },
        {
            "latitude": 36.753828,
            "longitude": 127.975773
        },
        {
            "latitude": 36.753793,
            "longitude": 127.975827
        },
        {
            "latitude": 36.753663,
            "longitude": 127.975888
        },
        {
            "latitude": 36.753492,
            "longitude": 127.976015
        },
        {
            "latitude": 36.753353,
            "longitude": 127.976055
        },
        {
            "latitude": 36.75292,
            "longitude": 127.976157
        },
        {
            "latitude": 36.752808,
            "longitude": 127.976203
        },
        {
            "latitude": 36.752675,
            "longitude": 127.9763
        },
        {
            "latitude": 36.752545,
            "longitude": 127.976328
        },
        {
            "latitude": 36.752443,
            "longitude": 127.976352
        },
        {
            "latitude": 36.75231,
            "longitude": 127.976318
        },
        {
            "latitude": 36.752242,
            "longitude": 127.976353
        },
        {
            "latitude": 36.75181,
            "longitude": 127.976425
        },
        {
            "latitude": 36.75171,
            "longitude": 127.976448
        },
        {
            "latitude": 36.751652,
            "longitude": 127.976392
        },
        {
            "latitude": 36.751477,
            "longitude": 127.976392
        },
        {
            "latitude": 36.75127,
            "longitude": 127.976208
        },
        {
            "latitude": 36.751178,
            "longitude": 127.976068
        },
        {
            "latitude": 36.751025,
            "longitude": 127.975938
        },
        {
            "latitude": 36.750932,
            "longitude": 127.975865
        },
        {
            "latitude": 36.75083,
            "longitude": 127.975787
        },
        {
            "latitude": 36.75065,
            "longitude": 127.975692
        },
        {
            "latitude": 36.750532,
            "longitude": 127.975563
        },
        {
            "latitude": 36.75038,
            "longitude": 127.975475
        },
        {
            "latitude": 36.750267,
            "longitude": 127.975342
        },
        {
            "latitude": 36.750022,
            "longitude": 127.975203
        },
        {
            "latitude": 36.74969,
            "longitude": 127.974955
        },
        {
            "latitude": 36.749615,
            "longitude": 127.974892
        },
        {
            "latitude": 36.749522,
            "longitude": 127.974803
        },
        {
            "latitude": 36.749342,
            "longitude": 127.974757
        },
        {
            "latitude": 36.748932,
            "longitude": 127.974432
        },
        {
            "latitude": 36.748597,
            "longitude": 127.974013
        },
        {
            "latitude": 36.74834,
            "longitude": 127.97368
        },
        {
            "latitude": 36.748237,
            "longitude": 127.973385
        },
        {
            "latitude": 36.748167,
            "longitude": 127.973322
        },
        {
            "latitude": 36.7479,
            "longitude": 127.972935
        },
        {
            "latitude": 36.747757,
            "longitude": 127.97275
        },
        {
            "latitude": 36.74766,
            "longitude": 127.9727
        },
        {
            "latitude": 36.747175,
            "longitude": 127.972168
        },
        {
            "latitude": 36.747002,
            "longitude": 127.972072
        },
        {
            "latitude": 36.746705,
            "longitude": 127.971807
        },
        {
            "latitude": 36.746598,
            "longitude": 127.971715
        },
        {
            "latitude": 36.746507,
            "longitude": 127.971605
        },
        {
            "latitude": 36.746125,
            "longitude": 127.971212
        },
        {
            "latitude": 36.746002,
            "longitude": 127.97104
        },
        {
            "latitude": 36.745943,
            "longitude": 127.970915
        },
        {
            "latitude": 36.74586,
            "longitude": 127.970627
        },
        {
            "latitude": 36.74572,
            "longitude": 127.970342
        },
        {
            "latitude": 36.745683,
            "longitude": 127.970218
        },
        {
            "latitude": 36.745522,
            "longitude": 127.969928
        },
        {
            "latitude": 36.745472,
            "longitude": 127.969832
        },
        {
            "latitude": 36.745408,
            "longitude": 127.969752
        },
        {
            "latitude": 36.745197,
            "longitude": 127.969682
        },
        {
            "latitude": 36.745007,
            "longitude": 127.96966
        },
        {
            "latitude": 36.744937,
            "longitude": 127.96958
        },
        {
            "latitude": 36.744848,
            "longitude": 127.969457
        },
        {
            "latitude": 36.744725,
            "longitude": 127.969372
        },
        {
            "latitude": 36.744637,
            "longitude": 127.969332
        },
        {
            "latitude": 36.744548,
            "longitude": 127.969335
        },
        {
            "latitude": 36.744493,
            "longitude": 127.969248
        },
        {
            "latitude": 36.744363,
            "longitude": 127.969238
        },
        {
            "latitude": 36.744105,
            "longitude": 127.969168
        },
        {
            "latitude": 36.744005,
            "longitude": 127.969125
        },
        {
            "latitude": 36.743902,
            "longitude": 127.969072
        },
        {
            "latitude": 36.743835,
            "longitude": 127.969038
        },
        {
            "latitude": 36.743742,
            "longitude": 127.96897
        },
        {
            "latitude": 36.743433,
            "longitude": 127.968753
        },
        {
            "latitude": 36.743433,
            "longitude": 127.968753
        },
        {
            "latitude": 36.743298,
            "longitude": 127.968723
        },
        {
            "latitude": 36.743188,
            "longitude": 127.968558
        },
        {
            "latitude": 36.743103,
            "longitude": 127.968465
        },
        {
            "latitude": 36.742928,
            "longitude": 127.96838
        },
        {
            "latitude": 36.74278,
            "longitude": 127.968258
        },
        {
            "latitude": 36.742728,
            "longitude": 127.968158
        },
        {
            "latitude": 36.742668,
            "longitude": 127.968018
        },
        {
            "latitude": 36.74255,
            "longitude": 127.967915
        },
        {
            "latitude": 36.742447,
            "longitude": 127.967877
        },
        {
            "latitude": 36.742323,
            "longitude": 127.96779
        },
        {
            "latitude": 36.742252,
            "longitude": 127.967682
        },
        {
            "latitude": 36.742208,
            "longitude": 127.967542
        },
        {
            "latitude": 36.742343,
            "longitude": 127.96741
        },
        {
            "latitude": 36.742207,
            "longitude": 127.96718
        },
        {
            "latitude": 36.742105,
            "longitude": 127.967072
        },
        {
            "latitude": 36.74207,
            "longitude": 127.966962
        },
        {
            "latitude": 36.742007,
            "longitude": 127.9669
        },
        {
            "latitude": 36.741958,
            "longitude": 127.966763
        },
        {
            "latitude": 36.742003,
            "longitude": 127.966697
        },
        {
            "latitude": 36.741937,
            "longitude": 127.966557
        },
        {
            "latitude": 36.741885,
            "longitude": 127.966457
        },
        {
            "latitude": 36.741862,
            "longitude": 127.966305
        },
        {
            "latitude": 36.741875,
            "longitude": 127.966183
        },
        {
            "latitude": 36.741925,
            "longitude": 127.96597
        },
        {
            "latitude": 36.741918,
            "longitude": 127.965822
        },
        {
            "latitude": 36.741872,
            "longitude": 127.96569
        },
        {
            "latitude": 36.741825,
            "longitude": 127.965582
        },
        {
            "latitude": 36.741828,
            "longitude": 127.965473
        },
        {
            "latitude": 36.74189,
            "longitude": 127.965362
        },
        {
            "latitude": 36.7419,
            "longitude": 127.965107
        },
        {
            "latitude": 36.741867,
            "longitude": 127.964902
        },
        {
            "latitude": 36.741832,
            "longitude": 127.964795
        },
        {
            "latitude": 36.741817,
            "longitude": 127.964653
        },
        {
            "latitude": 36.741775,
            "longitude": 127.964502
        },
        {
            "latitude": 36.741747,
            "longitude": 127.964258
        },
        {
            "latitude": 36.741828,
            "longitude": 127.964202
        },
        {
            "latitude": 36.741968,
            "longitude": 127.964187
        },
        {
            "latitude": 36.74206,
            "longitude": 127.964132
        },
        {
            "latitude": 36.742162,
            "longitude": 127.964128
        },
        {
            "latitude": 36.742325,
            "longitude": 127.964092
        },
        {
            "latitude": 36.742422,
            "longitude": 127.964115
        },
        {
            "latitude": 36.742528,
            "longitude": 127.964143
        },
        {
            "latitude": 36.742648,
            "longitude": 127.964158
        },
        {
            "latitude": 36.742753,
            "longitude": 127.964115
        },
        {
            "latitude": 36.742832,
            "longitude": 127.964037
        },
        {
            "latitude": 36.742948,
            "longitude": 127.963972
        },
        {
            "latitude": 36.743052,
            "longitude": 127.9639
        },
        {
            "latitude": 36.743198,
            "longitude": 127.963917
        },
        {
            "latitude": 36.743603,
            "longitude": 127.963667
        },
        {
            "latitude": 36.743873,
            "longitude": 127.963598
        },
        {
            "latitude": 36.743983,
            "longitude": 127.963573
        },
        {
            "latitude": 36.744193,
            "longitude": 127.963572
        },
        {
            "latitude": 36.744303,
            "longitude": 127.963608
        },
        {
            "latitude": 36.744405,
            "longitude": 127.963613
        },
        {
            "latitude": 36.7447,
            "longitude": 127.963627
        },
        {
            "latitude": 36.744902,
            "longitude": 127.963678
        },
        {
            "latitude": 36.744983,
            "longitude": 127.963747
        },
        {
            "latitude": 36.7451,
            "longitude": 127.963778
        },
        {
            "latitude": 36.745197,
            "longitude": 127.96382
        },
        {
            "latitude": 36.745292,
            "longitude": 127.96385
        },
        {
            "latitude": 36.74539,
            "longitude": 127.96383
        },
        {
            "latitude": 36.745797,
            "longitude": 127.963898
        },
        {
            "latitude": 36.745933,
            "longitude": 127.963933
        },
        {
            "latitude": 36.746065,
            "longitude": 127.963977
        },
        {
            "latitude": 36.746165,
            "longitude": 127.964015
        },
        {
            "latitude": 36.746307,
            "longitude": 127.964055
        },
        {
            "latitude": 36.746485,
            "longitude": 127.964072
        },
        {
            "latitude": 36.746627,
            "longitude": 127.964125
        },
        {
            "latitude": 36.746727,
            "longitude": 127.964067
        },
        {
            "latitude": 36.746823,
            "longitude": 127.96408
        },
        {
            "latitude": 36.746922,
            "longitude": 127.96409
        },
        {
            "latitude": 36.747025,
            "longitude": 127.964065
        },
        {
            "latitude": 36.747132,
            "longitude": 127.964083
        },
        {
            "latitude": 36.74736,
            "longitude": 127.964127
        },
        {
            "latitude": 36.747478,
            "longitude": 127.964178
        },
        {
            "latitude": 36.74759,
            "longitude": 127.964163
        },
        {
            "latitude": 36.747698,
            "longitude": 127.964138
        },
        {
            "latitude": 36.747823,
            "longitude": 127.964132
        },
        {
            "latitude": 36.747997,
            "longitude": 127.964177
        },
        {
            "latitude": 36.748143,
            "longitude": 127.964213
        },
        {
            "latitude": 36.748233,
            "longitude": 127.964285
        },
        {
            "latitude": 36.748343,
            "longitude": 127.964308
        },
        {
            "latitude": 36.74844,
            "longitude": 127.964298
        },
        {
            "latitude": 36.748723,
            "longitude": 127.964347
        },
        {
            "latitude": 36.74872,
            "longitude": 127.96456
        },
        {
            "latitude": 36.748772,
            "longitude": 127.964718
        },
        {
            "latitude": 36.748857,
            "longitude": 127.964783
        },
        {
            "latitude": 36.748932,
            "longitude": 127.964868
        },
        {
            "latitude": 36.749033,
            "longitude": 127.964927
        },
        {
            "latitude": 36.749117,
            "longitude": 127.964972
        },
        {
            "latitude": 36.749215,
            "longitude": 127.964952
        },
        {
            "latitude": 36.749348,
            "longitude": 127.964968
        },
        {
            "latitude": 36.749467,
            "longitude": 127.965025
        },
        {
            "latitude": 36.749598,
            "longitude": 127.965012
        },
        {
            "latitude": 36.750048,
            "longitude": 127.96503
        },
        {
            "latitude": 36.750205,
            "longitude": 127.965008
        },
        {
            "latitude": 36.750355,
            "longitude": 127.965085
        },
        {
            "latitude": 36.750457,
            "longitude": 127.965122
        },
        {
            "latitude": 36.750577,
            "longitude": 127.965103
        },
        {
            "latitude": 36.750773,
            "longitude": 127.965137
        },
        {
            "latitude": 36.750898,
            "longitude": 127.965153
        },
        {
            "latitude": 36.751078,
            "longitude": 127.96528
        },
        {
            "latitude": 36.751217,
            "longitude": 127.965332
        },
        {
            "latitude": 36.751338,
            "longitude": 127.965363
        },
        {
            "latitude": 36.751428,
            "longitude": 127.965387
        },
        {
            "latitude": 36.75178,
            "longitude": 127.965552
        },
        {
            "latitude": 36.751922,
            "longitude": 127.965612
        },
        {
            "latitude": 36.752078,
            "longitude": 127.965658
        },
        {
            "latitude": 36.75216,
            "longitude": 127.965725
        },
        {
            "latitude": 36.752362,
            "longitude": 127.965777
        },
        {
            "latitude": 36.752475,
            "longitude": 127.965822
        },
        {
            "latitude": 36.752603,
            "longitude": 127.965888
        },
        {
            "latitude": 36.752715,
            "longitude": 127.965912
        },
        {
            "latitude": 36.75299,
            "longitude": 127.966007
        },
        {
            "latitude": 36.753098,
            "longitude": 127.966035
        },
        {
            "latitude": 36.753162,
            "longitude": 127.966067
        },
        {
            "latitude": 36.753232,
            "longitude": 127.96615
        },
        {
            "latitude": 36.75332,
            "longitude": 127.966297
        },
        {
            "latitude": 36.753417,
            "longitude": 127.966402
        },
        {
            "latitude": 36.753463,
            "longitude": 127.966528
        },
        {
            "latitude": 36.753553,
            "longitude": 127.966595
        },
        {
            "latitude": 36.753647,
            "longitude": 127.966688
        },
        {
            "latitude": 36.753722,
            "longitude": 127.966745
        },
        {
            "latitude": 36.753808,
            "longitude": 127.966897
        },
        {
            "latitude": 36.753903,
            "longitude": 127.967017
        },
        {
            "latitude": 36.753968,
            "longitude": 127.967103
        },
        {
            "latitude": 36.754028,
            "longitude": 127.967222
        },
        {
            "latitude": 36.754085,
            "longitude": 127.967325
        },
        {
            "latitude": 36.754157,
            "longitude": 127.967432
        },
        {
            "latitude": 36.75425,
            "longitude": 127.96753
        },
        {
            "latitude": 36.754472,
            "longitude": 127.96768
        },
        {
            "latitude": 36.754565,
            "longitude": 127.967728
        },
        {
            "latitude": 36.754628,
            "longitude": 127.967828
        },
        {
            "latitude": 36.754733,
            "longitude": 127.96787
        },
        {
            "latitude": 36.75482,
            "longitude": 127.96796
        },
        {
            "latitude": 36.754738,
            "longitude": 127.968115
        },
        {
            "latitude": 36.754622,
            "longitude": 127.968185
        },
        {
            "latitude": 36.754602,
            "longitude": 127.968292
        },
        {
            "latitude": 36.754688,
            "longitude": 127.968362
        },
        {
            "latitude": 36.754703,
            "longitude": 127.968468
        },
        {
            "latitude": 36.754732,
            "longitude": 127.968608
        },
        {
            "latitude": 36.754793,
            "longitude": 127.968707
        },
        {
            "latitude": 36.754873,
            "longitude": 127.968752
        },
        {
            "latitude": 36.754902,
            "longitude": 127.968873
        },
        {
            "latitude": 36.75497,
            "longitude": 127.968977
        },
        {
            "latitude": 36.755027,
            "longitude": 127.969085
        },
        {
            "latitude": 36.755087,
            "longitude": 127.969123
        },
        {
            "latitude": 36.755182,
            "longitude": 127.96917
        },
        {
            "latitude": 36.755255,
            "longitude": 127.96923
        },
        {
            "latitude": 36.755272,
            "longitude": 127.969385
        },
        {
            "latitude": 36.755177,
            "longitude": 127.969365
        },
        {
            "latitude": 36.755082,
            "longitude": 127.96949
        },
        {
            "latitude": 36.755033,
            "longitude": 127.969592
        },
        {
            "latitude": 36.755028,
            "longitude": 127.969713
        },
        {
            "latitude": 36.755035,
            "longitude": 127.969825
        },
        {
            "latitude": 36.755057,
            "longitude": 127.96994
        },
        {
            "latitude": 36.755088,
            "longitude": 127.970057
        },
        {
            "latitude": 36.755093,
            "longitude": 127.970162
        },
        {
            "latitude": 36.755105,
            "longitude": 127.970273
        },
        {
            "latitude": 36.755162,
            "longitude": 127.970415
        },
        {
            "latitude": 36.755125,
            "longitude": 127.97055
        },
        {
            "latitude": 36.755107,
            "longitude": 127.970652
        },
        {
            "latitude": 36.755117,
            "longitude": 127.970755
        },
        {
            "latitude": 36.755163,
            "longitude": 127.970863
        },
        {
            "latitude": 36.755118,
            "longitude": 127.970935
        },
        {
            "latitude": 36.755158,
            "longitude": 127.97107
        },
        {
            "latitude": 36.755192,
            "longitude": 127.971242
        },
        {
            "latitude": 36.755185,
            "longitude": 127.971343
        },
        {
            "latitude": 36.755188,
            "longitude": 127.971462
        },
        {
            "latitude": 36.755243,
            "longitude": 127.971583
        },
        {
            "latitude": 36.755233,
            "longitude": 127.971707
        },
        {
            "latitude": 36.755278,
            "longitude": 127.971822
        },
        {
            "latitude": 36.755255,
            "longitude": 127.971922
        },
        {
            "latitude": 36.755215,
            "longitude": 127.97202
        },
        {
            "latitude": 36.755113,
            "longitude": 127.972053
        },
        {
            "latitude": 36.755083,
            "longitude": 127.972173
        },
        {
            "latitude": 36.755025,
            "longitude": 127.972273
        },
        {
            "latitude": 36.754942,
            "longitude": 127.972328
        },
        {
            "latitude": 36.754893,
            "longitude": 127.972432
        },
        {
            "latitude": 36.75491,
            "longitude": 127.972502
        },
        {
            "latitude": 36.754953,
            "longitude": 127.972578
        },
        {
            "latitude": 36.755102,
            "longitude": 127.972547
        },
        {
            "latitude": 36.755225,
            "longitude": 127.972542
        },
        {
            "latitude": 36.755337,
            "longitude": 127.97249
        },
        {
            "latitude": 36.755428,
            "longitude": 127.972445
        },
        {
            "latitude": 36.755557,
            "longitude": 127.972443
        },
        {
            "latitude": 36.755687,
            "longitude": 127.972427
        },
        {
            "latitude": 36.75578,
            "longitude": 127.972548
        },
        {
            "latitude": 36.755843,
            "longitude": 127.972637
        },
        {
            "latitude": 36.755913,
            "longitude": 127.972748
        },
        {
            "latitude": 36.756018,
            "longitude": 127.972902
        },
        {
            "latitude": 36.756188,
            "longitude": 127.972833
        },
        {
            "latitude": 36.756178,
            "longitude": 127.972947
        },
        {
            "latitude": 36.756247,
            "longitude": 127.973052
        },
        {
            "latitude": 36.756347,
            "longitude": 127.973235
        },
        {
            "latitude": 36.756437,
            "longitude": 127.973275
        },
        {
            "latitude": 36.756518,
            "longitude": 127.97341
        },
        {
            "latitude": 36.756597,
            "longitude": 127.973547
        },
        {
            "latitude": 36.756675,
            "longitude": 127.973642
        },
        {
            "latitude": 36.756748,
            "longitude": 127.973735
        },
        {
            "latitude": 36.756912,
            "longitude": 127.97388
        },
        {
            "latitude": 36.757103,
            "longitude": 127.973922
        },
        {
            "latitude": 36.75729,
            "longitude": 127.973897
        },
        {
            "latitude": 36.757372,
            "longitude": 127.973925
        },
        {
            "latitude": 36.757457,
            "longitude": 127.974005
        },
        {
            "latitude": 36.757548,
            "longitude": 127.974083
        },
        {
            "latitude": 36.757693,
            "longitude": 127.974175
        },
        {
            "latitude": 36.7578,
            "longitude": 127.974247
        },
        {
            "latitude": 36.757958,
            "longitude": 127.974322
        },
        {
            "latitude": 36.75809,
            "longitude": 127.974448
        },
        {
            "latitude": 36.758118,
            "longitude": 127.974647
        },
        {
            "latitude": 36.758158,
            "longitude": 127.974823
        },
        {
            "latitude": 36.758177,
            "longitude": 127.974962
        },
        {
            "latitude": 36.758175,
            "longitude": 127.975162
        },
        {
            "latitude": 36.758225,
            "longitude": 127.975427
        },
        {
            "latitude": 36.758253,
            "longitude": 127.975563
        },
        {
            "latitude": 36.758302,
            "longitude": 127.975688
        },
        {
            "latitude": 36.758328,
            "longitude": 127.975832
        },
        {
            "latitude": 36.758318,
            "longitude": 127.97601
        },
        {
            "latitude": 36.758303,
            "longitude": 127.97619
        },
        {
            "latitude": 36.758303,
            "longitude": 127.97631
        },
        {
            "latitude": 36.758357,
            "longitude": 127.976462
        },
        {
            "latitude": 36.758437,
            "longitude": 127.976693
        },
        {
            "latitude": 36.7585,
            "longitude": 127.976913
        },
        {
            "latitude": 36.758555,
            "longitude": 127.977103
        },
        {
            "latitude": 36.758628,
            "longitude": 127.977232
        },
        {
            "latitude": 36.758713,
            "longitude": 127.977348
        }
    ],
    "total_distance": 5555.371320054121,
    "surface_distances": {},
    "surface_ratios": {}
}