{
    "coordinates": [
        {
            "latitude": 35.825,
            "longitude": 129.22431
        },
        {
            "latitude": 35.824819,
            "longitude": 129.224362
        },
        {
            "latitude": 35.82472,
            "longitude": 129.22443
        },
        {
            "latitude": 35.824543,
            "longitude": 129.224419
        },
        {
            "latitude": 35.824306,
            "longitude": 129.224484
        },
        {
            "latitude": 35.824108,
            "longitude": 129.224469
        },
        {
            "latitude": 35.823909,
            "longitude": 129.224476
        },
        {
            "latitude": 35.823687,
            "longitude": 129.22438
        },
        {
            "latitude": 35.823444,
            "longitude": 129.224192
        },
        {
            "latitude": 35.823173,
            "longitude": 129.224114
        },
        {
            "latitude": 35.82294,
            "longitude": 129.224024
        },
        {
            "latitude": 35.822718,
            "longitude": 129.223967
        },
        {
            "latitude": 35.822474,
            "longitude": 129.223907
        },
        {
            "latitude": 35.822263,
            "longitude": 129.223895
        },
        {
            "latitude": 35.822009,
            "longitude": 129.223951
        },
        {
            "latitude": 35.821728,
            "longitude": 129.223957
        },
        {
            "latitude": 35.821547,
            "longitude": 129.224047
        },
        {
            "latitude": 35.821319,
            "longitude": 129.224042
        },
        {
            "latitude": 35.821041,
            "longitude": 129.2241
        },
        {
            "latitude": 35.820756,
            "longitude": 129.224077
        },
        {
            "latitude": 35.820526,
            "longitude": 129.22425
        },
        {
            "latitude": 35.820316,
            "longitude": 129.224337
        },
        {
            "latitude": 35.820079,
            "longitude": 129.224452
        },
        {
            "latitude": 35.819861,
            "longitude": 129.224523
        },
        {
            "latitude": 35.819677,
            "longitude": 129.224753
        },
        {
            "latitude": 35.819383,
            "longitude": 129.224829
        },
        {
            "latitude": 35.819141,
            "longitude": 129.224768
        },
        {
            "latitude": 35.818825,
            "longitude": 129.224722
        },
        {
            "latitude": 35.818585,
            "longitude": 129.224659
        },
        {
            "latitude": 35.818295,
            "longitude": 129.224804
        },
        {
            "latitude": 35.818077,
            "longitude": 129.224995
        },
        {
            "latitude": 35.817923,
            "longitude": 129.22516
        },
        {
            "latitude": 35.817746,
            "longitude": 129.225344
        },
        {
            "latitude": 35.817567,
            "longitude": 129.225517
        },
        {
            "latitude": 35.817408,
            "longitude": 129.225753
        },
        {
            "latitude": 35.817432,
            "longitude": 129.226069
        },
        {
            "latitude": 35.817223,
            "longitude": 129.226288
        },
        {
            "latitude": 35.81701,
            "longitude": 129.226428
        },
        {
            "latitude": 35.816835,
            "longitude": 129.226641
        },
        {
            "latitude": 35.81675,
            "longitude": 129.227106
        },
        {
            "latitude": 35.816686,
            "longitude": 129.227426
        },
        {
            "latitude": 35.816437,
            "longitude": 129.227527
        },
        {
            "latitude": 35.816154,
            "longitude": 129.227529
        },
        {
            "latitude": 35.815927,
            "longitude": 129.227553
        },
        {
            "latitude": 35.815714,
            "longitude": 129.227574
        },
        {
            "latitude": 35.815475,
            "longitude": 129.227769
        },
        {
            "latitude": 35.815087,
            "longitude": 129.22785
        },
        {
            "latitude": 35.814876,
            "longitude": 129.227872
        },
        {
            "latitude": 35.814685,
            "longitude": 129.227799
        },
        {
            "latitude": 35.814516,
            "longitude": 129.227665
        },
        {
            "latitude": 35.814299,
            "longitude": 129.227855
        },
        {
            "latitude": 35.814114,
            "longitude": 129.228005
        },
        {
            "latitude": 35.813927,
            "longitude": 129.228065
        },
        {
            "latitude": 35.813671,
            "longitude": 129.228062
        },
        {
            "latitude": 35.81342,
            "longitude": 129.228005
        },
        {
            "latitude": 35.813234,
            "longitude": 129.228032
        },
        {
            "latitude": 35.813039,
            "longitude": 129.228133
        },
        {
            "latitude": 35.812723,
            "longitude": 129.228061
        },
        {
            "latitude": 35.812683,
            "longitude": 129.22789
        },
        {
            "latitude": 35.812608,
            "longitude": 129.22769
        },
        {
            "latitude": 35.81244,
            "longitude": 129.227494
        },
        {
            "latitude": 35.812173,
            "longitude": 129.227479
        },
        {
            "latitude": 35.811973,
            "longitude": 129.227542
        },
        {
            "latitude": 35.811818,
            "longitude": 129.227649
        },
        {
            "latitude": 35.811528,
            "longitude": 129.227614
        },
        {
            "latitude": 35.81136,
            "longitude": 129.227423
        },
        {
            "latitude": 35.811126,
            "longitude": 129.227305
        },
        {
            "latitude": 35.810905,
            "longitude": 129.227263
        },
        {
            "latitude": 35.810691,
            "longitude": 129.227264
        },
        {
            "latitude": 35.810429,
            "longitude": 129.227323
        },
        {
            "latitude": 35.810184,
            "longitude": 129.227353
        },
        {
            "latitude": 35.810024,
            "longitude": 129.227218
        },
        {
            "latitude": 35.809735,
            "longitude": 129.227232
        },
        {
            "latitude": 35.809458,
            "longitude": 129.227346
        },
        {
            "latitude": 35.809302,
            "longitude": 129.227464
        },
        {
            "latitude": 35.809044,
            "longitude": 129.227537
        },
        {
            "latitude": 35.808768,
            "longitude": 129.227438
        },
        {
            "latitude": 35.80858,
            "longitude": 129.227524
        },
        {
            "latitude": 35.808392,
            "longitude": 129.227497
        },
        {
            "latitude": 35.808177,
            "longitude": 129.227497
        },
        {
            "latitude": 35.808004,
            "longitude": 129.227595
        },
        {
            "latitude": 35.807785,
            "longitude": 129.227701
        },
        {
            "latitude": 35.807546,
            "longitude": 129.22777
        },
        {
            "latitude": 35.807336,
            "longitude": 129.227774
        },
        {
            "latitude": 35.807142,
            "longitude": 129.227737
        },
        {
            "latitude": 35.807014,
            "longitude": 129.22768
        },
        {
            "latitude": 35.806892,
            "longitude": 129.227781
        },
        {
            "latitude": 35.806652,
            "longitude": 129.227884
        },
        {
            "latitude": 35.806366,
            "longitude": 129.228022
        },
        {
            "latitude": 35.806122,
            "longitude": 129.228269
        },
        {
            "latitude": 35.80596,
            "longitude": 129.228437
        },
        {
            "latitude": 35.805719,
            "longitude": 129.228538
        },
        {
            "latitude": 35.805568,
            "longitude": 129.228692
        },
        {
            "latitude": 35.805358,
            "longitude": 129.228786
        },
        {
            "latitude": 35.805111,
            "longitude": 129.228861
        },
        {
            "latitude": 35.804875,
            "longitude": 129.229065
        },
        {
            "latitude": 35.804708,
            "longitude": 129.229191
        },
        {
            "latitude": 35.804429,
            "longitude": 129.229245
        },
        {
            "latitude": 35.804207,
            "longitude": 129.229327
        },
        {
            "latitude": 35.804035,
            "longitude": 129.229266
        },
        {
            "latitude": 35.80394,
            "longitude": 129.229254
        },
        {
            "latitude": 35.803833,
            "longitude": 129.229243
        },
        {
            "latitude": 35.80355,
            "longitude": 129.229361
        },
        {
            "latitude": 35.803312,
            "longitude": 129.22933
        },
        {
            "latitude": 35.803043,
            "longitude": 129.229304
        },
        {
            "latitude": 35.802796,
            "longitude": 129.229496
        },
        {
            "latitude": 35.802527,
            "longitude": 129.229506
        },
        {
            "latitude": 35.8023,
            "longitude": 129.229436
        },
        {
            "latitude": 35.802,
            "longitude": 129.229404
        },
        {
            "latitude": 35.801687,
            "longitude": 129.229462
        },
        {
            "latitude": 35.801272,
            "longitude": 129.229388
        },
        {
            "latitude": 35.801127,
            "longitude": 129.229149
        },
        {
            "latitude": 35.800827,
            "longitude": 129.228989
        },
        {
            "latitude": 35.800626,
            "longitude": 129.228957
        },
        {
            "latitude": 35.800447,
            "longitude": 129.22907
        },
        {
            "latitude": 35.800272,
            "longitude": 129.229301
        },
        {
            "latitude": 35.800107,
            "longitude": 129.229477
        },
        {
            "latitude": 35.799993,
            "longitude": 129.229505
        },
        {
            "latitude": 35.799705,
            "longitude": 129.229507
        },
        {
            "latitude": 35.799483,
            "longitude": 129.229605
        },
        {
            "latitude": 35.799324,
            "longitude": 129.229818
        },
        {
            "latitude": 35.799056,
            "longitude": 129.22999
        },
        {
            "latitude": 35.798818,
            "longitude": 129.229903
        },
        {
            "latitude": 35.798522,
            "longitude": 129.229779
        },
        {
            "latitude": 35.798177,
            "longitude": 129.22961
        },
        {
            "latitude": 35.797952,
            "longitude": 129.229545
        },
        {
            "latitude": 35.797708,
            "longitude": 129.229515
        },
        {
            "latitude": 35.797525,
            "longitude": 129.229621
        },
        {
            "latitude": 35.797342,
            "longitude": 129.229486
        },
        {
            "latitude": 35.797164,
            "longitude": 129.229385
        },
        {
            "latitude": 35.796965,
            "longitude": 129.229379
        },
        {
            "latitude": 35.796758,
            "longitude": 129.229203
        },
        {
            "latitude": 35.796492,
            "longitude": 129.229241
        },
        {
            "latitude": 35.796282,
            "longitude": 129.229149
        },
        {
            "latitude": 35.796068,
            "longitude": 129.229148
        },
        {
            "latitude": 35.795818,
            "longitude": 129.229095
        },
        {
            "latitude": 35.795588,
            "longitude": 129.228917
        },
        {
            "latitude": 35.79539,
            "longitude": 129.228671
        },
        {
            "latitude": 35.795191,
            "longitude": 129.228439
        },
        {
            "latitude": 35.795051,
            "longitude": 129.228229
        },
        {
            "latitude": 35.794852,
            "longitude": 129.22798
        },
        {
            "latitude": 35.794572,
            "longitude": 129.227782
        },
        {
            "latitude": 35.794353,
            "longitude": 129.227706
        },
        {
            "latitude": 35.794068,
            "longitude": 129.227699
        },
        {
            "latitude": 35.793896,
            "longitude": 129.227633
        },
        {
            "latitude": 35.793567,
            "longitude": 129.227606
        },
        {
            "latitude": 35.793436,
            "longitude": 129.227698
        },
        {
            "latitude": 35.793432,
            "longitude": 129.227699
        },
        {
            "latitude": 35.793359,
            "longitude": 129.22764
        },
        {
            "latitude": 35.793285,
            "longitude": 129.227575
        },
        {
            "latitude": 35.793085,
            "longitude": 129.227437
        },
        {
            "latitude": 35.792828,
            "longitude": 129.227308
        },
        {
            "latitude": 35.79259,
            "longitude": 129.227175
        },
        {
            "latitude": 35.79238,
            "longitude": 129.227075
        },
        {
            "latitude": 35.792128,
            "longitude": 129.226912
        },
        {
            "latitude": 35.791916,
            "longitude": 129.226873
        },
        {
            "latitude": 35.791602,
            "longitude": 129.22685
        },
        {
            "latitude": 35.791348,
            "longitude": 129.226893
        },
        {
            "latitude": 35.791067,
            "longitude": 129.22684
        },
        {
            "latitude": 35.790827,
            "longitude": 129.226785
        },
        {
            "latitude": 35.790601,
            "longitude": 129.226699
        },
        {
            "latitude": 35.790449,
            "longitude": 129.226534
        },
        {
            "latitude": 35.790422,
            "longitude": 129.22638
        },
        {
            "latitude": 35.790349,
            "longitude": 129.22611
        },
        {
            "latitude": 35.790202,
            "longitude": 129.225948
        },
        {
            "latitude": 35.790113,
            "longitude": 129.22566
        },
        {
            "latitude": 35.789894,
            "longitude": 129.225191
        },
        {
            "latitude": 35.789763,
            "longitude": 129.224935
        },
        {
            "latitude": 35.789556,
            "longitude": 129.224777
        },
        {
            "latitude": 35.789374,
            "longitude": 129.22456
        },
        {
            "latitude": 35.789163,
            "longitude": 129.224312
        },
        {
            "latitude": 35.789017,
            "longitude": 129.224111
        },
        {
            "latitude": 35.788806,
            "longitude": 129.223817
        },
        {
            "latitude": 35.788845,
            "longitude": 129.223702
        },
        {
            "latitude": 35.788824,
            "longitude": 129.223621
        },
        {
            "latitude": 35.788905,
            "longitude": 129.223515
        },
        {
            "latitude": 35.789114,
            "longitude": 129.223371
        },
        {
            "latitude": 35.789248,
            "longitude": 129.223139
        },
        {
            "latitude": 35.789433,
            "longitude": 129.223055
        },
        {
            "latitude": 35.789485,
            "longitude": 129.222983
        },
        {
            "latitude": 35.789225,
            "longitude": 129.2229
        },
        {
            "latitude": 35.789102,
            "longitude": 129.222871
        },
        {
            "latitude": 35.78893,
            "longitude": 129.222719
        },
        {
            "latitude": 35.788868,
            "longitude": 129.222732
        },
        {
            "latitude": 35.788779,
            "longitude": 129.222728
        },
        {
            "latitude": 35.788762,
            "longitude": 129.22272
        },
        {
            "latitude": 35.7887,
            "longitude": 129.222664
        },
        {
            "latitude": 35.788519,
            "longitude": 129.222771
        },
        {
            "latitude": 35.788295,
            "longitude": 129.222907
        },
        {
            "latitude": 35.788071,
            "longitude": 129.222777
        },
        {
            "latitude": 35.787789,
            "longitude": 129.222779
        },
        {
            "latitude": 35.7876,
            "longitude": 129.222742
        },
        {
            "latitude": 35.787417,
            "longitude": 129.222901
        },
        {
            "latitude": 35.787118,
            "longitude": 129.223143
        },
        {
            "latitude": 35.786935,
            "longitude": 129.223175
        },
        {
            "latitude": 35.786667,
            "longitude": 129.223113
        },
        {
            "latitude": 35.786404,
            "longitude": 129.223089
        },
        {
            "latitude": 35.786168,
            "longitude": 129.223007
        },
        {
            "latitude": 35.785731,
            "longitude": 129.222911
        },
        {
            "latitude": 35.785483,
            "longitude": 129.222977
        },
        {
            "latitude": 35.785187,
            "longitude": 129.223054
        },
        {
            "latitude": 35.784913,
            "longitude": 129.223102
        },
        {
            "latitude": 35.784596,
            "longitude": 129.22313
        },
        {
            "latitude": 35.784324,
            "longitude": 129.223247
        },
        {
            "latitude": 35.784153,
            "longitude": 129.22349
        },
        {
            "latitude": 35.784096,
            "longitude": 129.223544
        },
        {
            "latitude": 35.784147,
            "longitude": 129.22368
        },
        {
            "latitude": 35.78421,
            "longitude": 129.223971
        },
        {
            "latitude": 35.78405,
            "longitude": 129.224222
        },
        {
            "latitude": 35.783858,
            "longitude": 129.224375
        },
        {
            "latitude": 35.78372,
            "longitude": 129.224599
        },
        {
            "latitude": 35.783771,
            "longitude": 129.224854
        },
        {
            "latitude": 35.783552,
            "longitude": 129.225118
        },
        {
            "latitude": 35.783364,
            "longitude": 129.225236
        },
        {
            "latitude": 35.783254,
            "longitude": 129.225428
        },
        {
            "latitude": 35.783215,
            "longitude": 129.225469
        },
        {
            "latitude": 35.78311,
            "longitude": 129.225615
        },
        {
            "latitude": 35.783062,
            "longitude": 129.225692
        },
        {
            "latitude": 35.783027,
            "longitude": 129.225706
        },
        {
            "latitude": 35.783056,
            "longitude": 129.225814
        },
        {
            "latitude": 35.783082,
            "longitude": 129.226095
        },
        {
            "latitude": 35.783335,
            "longitude": 129.226098
        },
        {
            "latitude": 35.783554,
            "longitude": 129.226095
        },
        {
            "latitude": 35.783766,
            "longitude": 129.226099
        },
        {
            "latitude": 35.783859,
            "longitude": 129.226291
        },
        {
            "latitude": 35.783851,
            "longitude": 129.226563
        },
        {
            "latitude": 35.783814,
            "longitude": 129.226866
        },
        {
            "latitude": 35.783785,
            "longitude": 129.227192
        },
        {
            "latitude": 35.783784,
            "longitude": 129.227435
        },
        {
            "latitude": 35.783833,
            "longitude": 129.22769
        },
        {
            "latitude": 35.783811,
            "longitude": 129.228035
        },
        {
            "latitude": 35.783552,
            "longitude": 129.228368
        },
        {
            "latitude": 35.783358,
            "longitude": 129.22848
        },
        {
            "latitude": 35.783131,
            "longitude": 129.228576
        },
        {
            "latitude": 35.782896,
            "longitude": 129.228674
        },
        {
            "latitude": 35.782616,
            "longitude": 129.228749
        },
        {
            "latitude": 35.782363,
            "longitude": 129.228857
        },
        {
            "latitude": 35.782076,
            "longitude": 129.228989
        },
        {
            "latitude": 35.781839,
            "longitude": 129.229065
        },
        {
            "latitude": 35.781823,
            "longitude": 129.229073
        },
        {
            "latitude": 35.781706,
            "longitude": 129.229148
        },
        {
            "latitude": 35.781552,
            "longitude": 129.229336
        },
        {
            "latitude": 35.781386,
            "longitude": 129.229651
        },
        {
            "latitude": 35.78127,
            "longitude": 129.229881
        },
        {
            "latitude": 35.781177,
            "longitude": 129.230173
        },
        {
            "latitude": 35.781231,
            "longitude": 129.230442
        },
        {
            "latitude": 35.781429,
            "longitude": 129.230593
        },
        {
            "latitude": 35.781575,
            "longitude": 129.230854
        },
        {
            "latitude": 35.781489,
            "longitude": 129.23108
        },
        {
            "latitude": 35.78126,
            "longitude": 129.231087
        },
        {
            "latitude": 35.781011,
            "longitude": 129.23114
        },
        {
            "latitude": 35.781224,
            "longitude": 129.23134
        },
        {
            "latitude": 35.781399,
            "longitude": 129.231541
        },
        {
            "latitude": 35.781623,
            "longitude": 129.231867
        },
        {
            "latitude": 35.781845,
            "longitude": 129.232031
        },
        {
            "latitude": 35.782088,
            "longitude": 129.232059
        },
        {
            "latitude": 35.782301,
            "longitude": 129.23222
        },
        {
            "latitude": 35.782542,
            "longitude": 129.232459
        },
        {
            "latitude": 35.782701,
            "longitude": 129.232591
        },
        {
            "latitude": 35.782833,
            "longitude": 129.232798
        },
        {
            "latitude": 35.782999,
            "longitude": 129.232907
        },
        {
            "latitude": 35.783272,
            "longitude": 129.233119
        },
        {
            "latitude": 35.783457,
            "longitude": 129.233309
        },
        {
            "latitude": 35.783624,
            "longitude": 129.233486
        },
        {
            "latitude": 35.783947,
            "longitude": 129.233711
        },
        {
            "latitude": 35.784149,
            "longitude": 129.233795
        },
        {
            "latitude": 35.784301,
            "longitude": 129.233778
        },
        {
            "latitude": 35.784491,
            "longitude": 129.23383
        },
        {
            "latitude": 35.784799,
            "longitude": 129.233826
        },
        {
            "latitude": 35.785013,
            "longitude": 129.233937
        },
        {
            "latitude": 35.785238,
            "longitude": 129.234035
        },
        {
            "latitude": 35.785539,
            "longitude": 129.234174
        },
        {
            "latitude": 35.785757,
            "longitude": 129.234323
        },
        {
            "latitude": 35.785992,
            "longitude": 129.234466
        },
        {
            "latitude": 35.786233,
            "longitude": 129.234412
        },
        {
            "latitude": 35.786423,
            "longitude": 129.234384
        },
        {
            "latitude": 35.786872,
            "longitude": 129.234545
        },
        {
            "latitude": 35.787017,
            "longitude": 129.234692
        },
        {
            "latitude": 35.78716,
            "longitude": 129.234908
        },
        {
            "latitude": 35.787314,
            "longitude": 129.235126
        },
        {
            "latitude": 35.7875,
            "longitude": 129.235268
        },
        {
            "latitude": 35.787705,
            "longitude": 129.235482
        },
        {
            "latitude": 35.787889,
            "longitude": 129.235569
        },
        {
            "latitude": 35.787971,
            "longitude": 129.235878
        },
        {
            "latitude": 35.788126,
            "longitude": 129.236153
        },
        {
            "latitude": 35.788316,
            "longitude": 129.236393
        },
        {
            "latitude": 35.788434,
            "longitude": 129.236629
        },
        {
            "latitude": 35.788568,
            "longitude": 129.236839
        },
        {
            "latitude": 35.788725,
            "longitude": 129.237103
        },
        {
            "latitude": 35.788925,
            "longitude": 129.237261
        },
        {
            "latitude": 35.789146,
            "longitude": 129.237479
        },
        {
            "latitude": 35.789325,
            "longitude": 129.237646
        },
        {
            "latitude": 35.789545,
            "longitude": 129.237827
        },
        {
            "latitude": 35.78976,
            "longitude": 129.237992
        },
        {
            "latitude": 35.789946,
            "longitude": 129.238125
        },
        {
            "latitude": 35.79025,
            "longitude": 129.238308
        },
        {
            "latitude": 35.790284,
            "longitude": 129.238391
        },
        {
            "latitude": 35.790322,
            "longitude": 129.238522
        },
        {
            "latitude": 35.790508,
            "longitude": 129.238611
        },
        {
            "latitude": 35.790767,
            "longitude": 129.238799
        },
        {
            "latitude": 35.790934,
            "longitude": 129.238949
        },
        {
            "latitude": 35.791012,
            "longitude": 129.238992
        },
        {
            "latitude": 35.791113,
            "longitude": 129.239077
        },
        {
            "latitude": 35.791178,
            "longitude": 129.239173
        },
        {
            "latitude": 35.791321,
            "longitude": 129.239454
        },
        {
            "latitude": 35.791434,
            "longitude": 129.239749
        },
        {
            "latitude": 35.791612,
            "longitude": 129.239964
        },
        {
            "latitude": 35.791779,
            "longitude": 129.240185
        },
        {
            "latitude": 35.791944,
            "longitude": 129.240374
        },
        {
            "latitude": 35.792147,
            "longitude": 129.240648
        },
        {
            "latitude": 35.792372,
            "longitude": 129.240981
        },
        {
            "latitude": 35.792571,
            "longitude": 129.241245
        },
        {
            "latitude": 35.792769,
            "longitude": 129.241432
        },
        {
            "latitude": 35.792858,
            "longitude": 129.241739
        },
        {
            "latitude": 35.792976,
            "longitude": 129.241952
        },
        {
            "latitude": 35.793149,
            "longitude": 129.242171
        },
        {
            "latitude": 35.793284,
            "longitude": 129.242391
        },
        {
            "latitude": 35.793476,
            "longitude": 129.242651
        },
        {
            "latitude": 35.793736,
            "longitude": 129.242679
        },
        {
            "latitude": 35.794009,
            "longitude": 129.242493
        },
        {
            "latitude": 35.794205,
            "longitude": 129.242432
        },
        {
            "latitude": 35.794479,
            "longitude": 129.2425
        },
        {
            "latitude": 35.794767,
            "longitude": 129.242412
        },
        {
            "latitude": 35.795001,
            "longitude": 129.242294
        },
        {
            "latitude": 35.79525,
            "longitude": 129.242171
        },
        {
            "latitude": 35.795267,
            "longitude": 129.242101
        },
        {
            "latitude": 35.795429,
            "longitude": 129.242078
        },
        {
            "latitude": 35.795595,
            "longitude": 129.242034
        },
        {
            "latitude": 35.795708,
            "longitude": 129.241951
        },
        {
            "latitude": 35.795763,
            "longitude": 129.241931
        },
        {
            "latitude": 35.795799,
            "longitude": 129.241947
        },
        {
            "latitude": 35.795826,
            "longitude": 129.242078
        },
        {
            "latitude": 35.795882,
            "longitude": 129.242217
        },
        {
            "latitude": 35.796042,
            "longitude": 129.2422
        },
        {
            "latitude": 35.79623,
            "longitude": 129.242047
        },
        {
            "latitude": 35.796407,
            "longitude": 129.241883
        },
        {
            "latitude": 35.796592,
            "longitude": 129.241861
        },
        {
            "latitude": 35.796771,
            "longitude": 129.242116
        },
        {
            "latitude": 35.796859,
            "longitude": 129.242366
        },
        {
            "latitude": 35.797007,
            "longitude": 129.242319
        },
        {
            "latitude": 35.797141,
            "longitude": 129.242113
        },
        {
            "latitude": 35.797333,
            "longitude": 129.242261
        },
        {
            "latitude": 35.797432,
            "longitude": 129.242459
        },
        {
            "latitude": 35.797379,
            "longitude": 129.24271
        },
        {
            "latitude": 35.797354,
            "longitude": 129.243031
        },
        {
            "latitude": 35.797356,
            "longitude": 129.243107
        }
    ],
    "total_distance": 8843.425354821646,
    "surface_distances": {},
    "surface_ratios": {}
}