{
    "coordinates": [
        {
            "latitude": 35.250535,
            "longitude": 129.049471
        },
        {
            "latitude": 35.250571,
            "longitude": 129.049334
        },
        {
            "latitude": 35.250607,
            "longitude": 129.049245
        },
        {
            "latitude": 35.250707,
            "longitude": 129.049124
        },
        {
            "latitude": 35.250901,
            "longitude": 129.049004
        },
        {
            "latitude": 35.251007,
            "longitude": 129.048797
        },
        {
            "latitude": 35.251077,
            "longitude": 129.048687
        },
        {
            "latitude": 35.251099,
            "longitude": 129.048546
        },
        {
            "latitude": 35.251181,
            "longitude": 129.048487
        },
        {
            "latitude": 35.251265,
            "longitude": 129.048332
        },
        {
            "latitude": 35.251321,
            "longitude": 129.048232
        },
        {
            "latitude": 35.251358,
            "longitude": 129.048109
        },
        {
            "latitude": 35.251349,
            "longitude": 129.047994
        },
        {
            "latitude": 35.251372,
            "longitude": 129.047881
        },
        {
            "latitude": 35.251493,
            "longitude": 129.047828
        },
        {
            "latitude": 35.251575,
            "longitude": 129.047745
        },
        {
            "latitude": 35.251645,
            "longitude": 129.047673
        },
        {
            "latitude": 35.251677,
            "longitude": 129.047502
        },
        {
            "latitude": 35.251725,
            "longitude": 129.047367
        },
        {
            "latitude": 35.251747,
            "longitude": 129.047253
        },
        {
            "latitude": 35.251781,
            "longitude": 129.047034
        },
        {
            "latitude": 35.251763,
            "longitude": 129.046903
        },
        {
            "latitude": 35.251769,
            "longitude": 129.046734
        },
        {
            "latitude": 35.25173,
            "longitude": 129.04657
        },
        {
            "latitude": 35.251696,
            "longitude": 129.046459
        },
        {
            "latitude": 35.251638,
            "longitude": 129.046281
        },
        {
            "latitude": 35.251587,
            "longitude": 129.046143
        },
        {
            "latitude": 35.251535,
            "longitude": 129.046002
        },
        {
            "latitude": 35.251487,
            "longitude": 129.045841
        },
        {
            "latitude": 35.251484,
            "longitude": 129.045707
        },
        {
            "latitude": 35.251486,
            "longitude": 129.045695
        },
        {
            "latitude": 35.251597,
            "longitude": 129.045572
        },
        {
            "latitude": 35.251676,
            "longitude": 129.045545
        },
        {
            "latitude": 35.251797,
            "longitude": 129.045513
        },
        {
            "latitude": 35.251971,
            "longitude": 129.045487
        },
        {
            "latitude": 35.252075,
            "longitude": 129.045499
        },
        {
            "latitude": 35.252155,
            "longitude": 129.045575
        },
        {
            "latitude": 35.252222,
            "longitude": 129.045656
        },
        {
            "latitude": 35.252353,
            "longitude": 129.045732
        },
        {
            "latitude": 35.252428,
            "longitude": 129.045811
        },
        {
            "latitude": 35.252503,
            "longitude": 129.045781
        },
        {
            "latitude": 35.252548,
            "longitude": 129.045913
        },
        {
            "latitude": 35.25263,
            "longitude": 129.045937
        },
        {
            "latitude": 35.252688,
            "longitude": 129.046009
        },
        {
            "latitude": 35.252769,
            "longitude": 129.046038
        },
        {
            "latitude": 35.252732,
            "longitude": 129.046189
        },
        {
            "latitude": 35.252748,
            "longitude": 129.046299
        },
        {
            "latitude": 35.252804,
            "longitude": 129.046239
        },
        {
            "latitude": 35.252811,
            "longitude": 129.046241
        },
        {
            "latitude": 35.252902,
            "longitude": 129.046255
        },
        {
            "latitude": 35.252902,
            "longitude": 129.046255
        },
        {
            "latitude": 35.252997,
            "longitude": 129.046305
        },
        {
            "latitude": 35.253121,
            "longitude": 129.046301
        },
        {
            "latitude": 35.253214,
            "longitude": 129.046383
        },
        {
            "latitude": 35.253366,
            "longitude": 129.046512
        },
        {
            "latitude": 35.253502,
            "longitude": 129.046576
        },
        {
            "latitude": 35.253629,
            "longitude": 129.046653
        },
        {
            "latitude": 35.253739,
            "longitude": 129.046721
        },
        {
            "latitude": 35.253832,
            "longitude": 129.046801
        },
        {
            "latitude": 35.253899,
            "longitude": 129.046915
        },
        {
            "latitude": 35.253959,
            "longitude": 129.047002
        },
        {
            "latitude": 35.254132,
            "longitude": 129.047122
        },
        {
            "latitude": 35.254204,
            "longitude": 129.047223
        },
        {
            "latitude": 35.254268,
            "longitude": 129.047381
        },
        {
            "latitude": 35.254306,
            "longitude": 129.047506
        },
        {
            "latitude": 35.2544,
            "longitude": 129.047648
        },
        {
            "latitude": 35.254514,
            "longitude": 129.047691
        },
        {
            "latitude": 35.254606,
            "longitude": 129.047785
        },
        {
            "latitude": 35.254669,
            "longitude": 129.047909
        },
        {
            "latitude": 35.254689,
            "longitude": 129.04802
        },
        {
            "latitude": 35.254741,
            "longitude": 129.048107
        },
        {
            "latitude": 35.254824,
            "longitude": 129.048248
        },
        {
            "latitude": 35.254886,
            "longitude": 129.048377
        },
        {
            "latitude": 35.254908,
            "longitude": 129.048521
        },
        {
            "latitude": 35.254999,
            "longitude": 129.048584
        },
        {
            "latitude": 35.255097,
            "longitude": 129.048637
        },
        {
            "latitude": 35.255226,
            "longitude": 129.048581
        },
        {
            "latitude": 35.2553,
            "longitude": 129.04853
        },
        {
            "latitude": 35.255372,
            "longitude": 129.04845
        },
        {
            "latitude": 35.25542,
            "longitude": 129.048345
        },
        {
            "latitude": 35.255495,
            "longitude": 129.048267
        },
        {
            "latitude": 35.255616,
            "longitude": 129.048185
        },
        {
            "latitude": 35.255741,
            "longitude": 129.048171
        },
        {
            "latitude": 35.255856,
            "longitude": 129.048119
        },
        {
            "latitude": 35.255945,
            "longitude": 129.048068
        },
        {
            "latitude": 35.256056,
            "longitude": 129.048027
        },
        {
            "latitude": 35.256193,
            "longitude": 129.047998
        },
        {
            "latitude": 35.25629,
            "longitude": 129.047911
        },
        {
            "latitude": 35.256381,
            "longitude": 129.047846
        },
        {
            "latitude": 35.256464,
            "longitude": 129.04785
        },
        {
            "latitude": 35.256563,
            "longitude": 129.047824
        },
        {
            "latitude": 35.256665,
            "longitude": 129.047763
        },
        {
            "latitude": 35.256812,
            "longitude": 129.047863
        },
        {
            "latitude": 35.256884,
            "longitude": 129.047933
        },
        {
            "latitude": 35.256942,
            "longitude": 129.047789
        },
        {
            "latitude": 35.256946,
            "longitude": 129.047684
        },
        {
            "latitude": 35.256895,
            "longitude": 129.047559
        },
        {
            "latitude": 35.256922,
            "longitude": 129.047415
        },
        {
            "latitude": 35.256943,
            "longitude": 129.047196
        },
        {
            "latitude": 35.256987,
            "longitude": 129.047083
        },
        {
            "latitude": 35.257028,
            "longitude": 129.046968
        },
        {
            "latitude": 35.257068,
            "longitude": 129.046855
        },
        {
            "latitude": 35.256955,
            "longitude": 129.046798
        },
        {
            "latitude": 35.256901,
            "longitude": 129.046693
        },
        {
            "latitude": 35.256934,
            "longitude": 129.04654
        },
        {
            "latitude": 35.256934,
            "longitude": 129.04654
        },
        {
            "latitude": 35.257092,
            "longitude": 129.046402
        },
        {
            "latitude": 35.257159,
            "longitude": 129.046315
        },
        {
            "latitude": 35.257143,
            "longitude": 129.046213
        },
        {
            "latitude": 35.257081,
            "longitude": 129.046113
        },
        {
            "latitude": 35.25706,
            "longitude": 129.046031
        },
        {
            "latitude": 35.257077,
            "longitude": 129.045914
        },
        {
            "latitude": 35.257048,
            "longitude": 129.045765
        },
        {
            "latitude": 35.257164,
            "longitude": 129.045686
        },
        {
            "latitude": 35.257216,
            "longitude": 129.045565
        },
        {
            "latitude": 35.257237,
            "longitude": 129.045472
        },
        {
            "latitude": 35.257254,
            "longitude": 129.045364
        },
        {
            "latitude": 35.257242,
            "longitude": 129.045247
        },
        {
            "latitude": 35.257305,
            "longitude": 129.045178
        },
        {
            "latitude": 35.257357,
            "longitude": 129.045034
        },
        {
            "latitude": 35.257322,
            "longitude": 129.044907
        },
        {
            "latitude": 35.257384,
            "longitude": 129.044797
        },
        {
            "latitude": 35.25738,
            "longitude": 129.044675
        },
        {
            "latitude": 35.257389,
            "longitude": 129.044564
        },
        {
            "latitude": 35.257464,
            "longitude": 129.044602
        },
        {
            "latitude": 35.257564,
            "longitude": 129.044578
        },
        {
            "latitude": 35.257608,
            "longitude": 129.044459
        },
        {
            "latitude": 35.25765,
            "longitude": 129.044345
        },
        {
            "latitude": 35.257712,
            "longitude": 129.044205
        },
        {
            "latitude": 35.257699,
            "longitude": 129.044132
        },
        {
            "latitude": 35.257724,
            "longitude": 129.04398
        },
        {
            "latitude": 35.257731,
            "longitude": 129.04385
        },
        {
            "latitude": 35.257715,
            "longitude": 129.043786
        },
        {
            "latitude": 35.257678,
            "longitude": 129.043685
        },
        {
            "latitude": 35.25764,
            "longitude": 129.043565
        },
        {
            "latitude": 35.257603,
            "longitude": 129.043452
        },
        {
            "latitude": 35.257545,
            "longitude": 129.043366
        },
        {
            "latitude": 35.257481,
            "longitude": 129.043246
        },
        {
            "latitude": 35.257429,
            "longitude": 129.043134
        },
        {
            "latitude": 35.257424,
            "longitude": 129.042999
        },
        {
            "latitude": 35.257426,
            "longitude": 129.042884
        },
        {
            "latitude": 35.257437,
            "longitude": 129.042664
        },
        {
            "latitude": 35.257438,
            "longitude": 129.042527
        },
        {
            "latitude": 35.257494,
            "longitude": 129.042418
        },
        {
            "latitude": 35.25761,
            "longitude": 129.042277
        },
        {
            "latitude": 35.257677,
            "longitude": 129.042189
        },
        {
            "latitude": 35.257826,
            "longitude": 129.042072
        },
        {
            "latitude": 35.257915,
            "longitude": 129.042035
        },
        {
            "latitude": 35.258028,
            "longitude": 129.042001
        },
        {
            "latitude": 35.25806,
            "longitude": 129.041895
        },
        {
            "latitude": 35.258169,
            "longitude": 129.041845
        },
        {
            "latitude": 35.258252,
            "longitude": 129.041778
        },
        {
            "latitude": 35.258293,
            "longitude": 129.041654
        },
        {
            "latitude": 35.25837,
            "longitude": 129.041595
        },
        {
            "latitude": 35.258424,
            "longitude": 129.041497
        },
        {
            "latitude": 35.258491,
            "longitude": 129.041407
        },
        {
            "latitude": 35.258599,
            "longitude": 129.04143
        },
        {
            "latitude": 35.258699,
            "longitude": 129.041369
        },
        {
            "latitude": 35.258768,
            "longitude": 129.041226
        },
        {
            "latitude": 35.258792,
            "longitude": 129.041118
        },
        {
            "latitude": 35.258813,
            "longitude": 129.04099
        },
        {
            "latitude": 35.258832,
            "longitude": 129.040874
        },
        {
            "latitude": 35.258905,
            "longitude": 129.040762
        },
        {
            "latitude": 35.259009,
            "longitude": 129.04058
        },
        {
            "latitude": 35.259085,
            "longitude": 129.040464
        },
        {
            "latitude": 35.259156,
            "longitude": 129.04038
        },
        {
            "latitude": 35.259121,
            "longitude": 129.040191
        },
        {
            "latitude": 35.259127,
            "longitude": 129.040051
        },
        {
            "latitude": 35.259143,
            "longitude": 129.039897
        },
        {
            "latitude": 35.259177,
            "longitude": 129.039669
        },
        {
            "latitude": 35.259071,
            "longitude": 129.039532
        },
        {
            "latitude": 35.258951,
            "longitude": 129.039435
        },
        {
            "latitude": 35.258994,
            "longitude": 129.039179
        },
        {
            "latitude": 35.259063,
            "longitude": 129.039011
        },
        {
            "latitude": 35.259132,
            "longitude": 129.038891
        },
        {
            "latitude": 35.259249,
            "longitude": 129.038856
        },
        {
            "latitude": 35.259346,
            "longitude": 129.038789
        },
        {
            "latitude": 35.259387,
            "longitude": 129.038677
        },
        {
            "latitude": 35.259427,
            "longitude": 129.038575
        },
        {
            "latitude": 35.259508,
            "longitude": 129.038394
        },
        {
            "latitude": 35.259505,
            "longitude": 129.038238
        },
        {
            "latitude": 35.259489,
            "longitude": 129.038145
        },
        {
            "latitude": 35.259418,
            "longitude": 129.037987
        },
        {
            "latitude": 35.259481,
            "longitude": 129.037908
        },
        {
            "latitude": 35.259595,
            "longitude": 129.037851
        },
        {
            "latitude": 35.259662,
            "longitude": 129.0378
        },
        {
            "latitude": 35.259738,
            "longitude": 129.03773
        },
        {
            "latitude": 35.2598,
            "longitude": 129.037635
        },
        {
            "latitude": 35.259834,
            "longitude": 129.037437
        },
        {
            "latitude": 35.259796,
            "longitude": 129.037332
        },
        {
            "latitude": 35.259828,
            "longitude": 129.037193
        },
        {
            "latitude": 35.259769,
            "longitude": 129.037092
        },
        {
            "latitude": 35.259721,
            "longitude": 129.036995
        },
        {
            "latitude": 35.259625,
            "longitude": 129.036902
        },
        {
            "latitude": 35.259599,
            "longitude": 129.036796
        },
        {
            "latitude": 35.259545,
            "longitude": 129.036681
        },
        {
            "latitude": 35.259462,
            "longitude": 129.0366
        },
        {
            "latitude": 35.259383,
            "longitude": 129.036538
        },
        {
            "latitude": 35.259283,
            "longitude": 129.036365
        },
        {
            "latitude": 35.259242,
            "longitude": 129.036255
        },
        {
            "latitude": 35.259298,
            "longitude": 129.036004
        },
        {
            "latitude": 35.259344,
            "longitude": 129.035952
        },
        {
            "latitude": 35.259594,
            "longitude": 129.036114
        },
        {
            "latitude": 35.259655,
            "longitude": 129.036187
        },
        {
            "latitude": 35.259707,
            "longitude": 129.03628
        },
        {
            "latitude": 35.259707,
            "longitude": 129.03632
        },
        {
            "latitude": 35.259796,
            "longitude": 129.036382
        },
        {
            "latitude": 35.25988,
            "longitude": 129.036421
        },
        {
            "latitude": 35.260004,
            "longitude": 129.036495
        },
        {
            "latitude": 35.260095,
            "longitude": 129.03654
        },
        {
            "latitude": 35.260197,
            "longitude": 129.036611
        },
        {
            "latitude": 35.260205,
            "longitude": 129.036709
        },
        {
            "latitude": 35.260287,
            "longitude": 129.036789
        },
        {
            "latitude": 35.260338,
            "longitude": 129.03678
        },
        {
            "latitude": 35.260449,
            "longitude": 129.036739
        },
        {
            "latitude": 35.260563,
            "longitude": 129.036729
        },
        {
            "latitude": 35.260665,
            "longitude": 129.036764
        },
        {
            "latitude": 35.26077,
            "longitude": 129.036831
        },
        {
            "latitude": 35.260882,
            "longitude": 129.036859
        },
        {
            "latitude": 35.260981,
            "longitude": 129.036877
        },
        {
            "latitude": 35.261073,
            "longitude": 129.036951
        },
        {
            "latitude": 35.261171,
            "longitude": 129.036976
        },
        {
            "latitude": 35.261273,
            "longitude": 129.037022
        },
        {
            "latitude": 35.261386,
            "longitude": 129.037113
        },
        {
            "latitude": 35.261465,
            "longitude": 129.037159
        },
        {
            "latitude": 35.261541,
            "longitude": 129.037241
        },
        {
            "latitude": 35.261629,
            "longitude": 129.03735
        },
        {
            "latitude": 35.261735,
            "longitude": 129.037439
        },
        {
            "latitude": 35.26185,
            "longitude": 129.037534
        },
        {
            "latitude": 35.261999,
            "longitude": 129.037648
        },
        {
            "latitude": 35.262075,
            "longitude": 129.037742
        },
        {
            "latitude": 35.262144,
            "longitude": 129.03781
        },
        {
            "latitude": 35.262231,
            "longitude": 129.037897
        },
        {
            "latitude": 35.262278,
            "longitude": 129.038014
        },
        {
            "latitude": 35.262258,
            "longitude": 129.038138
        },
        {
            "latitude": 35.2623,
            "longitude": 129.038265
        },
        {
            "latitude": 35.262289,
            "longitude": 129.038415
        },
        {
            "latitude": 35.262319,
            "longitude": 129.038522
        },
        {
            "latitude": 35.262377,
            "longitude": 129.038634
        },
        {
            "latitude": 35.262347,
            "longitude": 129.038686
        },
        {
            "latitude": 35.26241,
            "longitude": 129.038793
        },
        {
            "latitude": 35.262442,
            "longitude": 129.038893
        },
        {
            "latitude": 35.262544,
            "longitude": 129.039103
        },
        {
            "latitude": 35.262589,
            "longitude": 129.03922
        },
        {
            "latitude": 35.262642,
            "longitude": 129.039325
        },
        {
            "latitude": 35.262718,
            "longitude": 129.039485
        },
        {
            "latitude": 35.262757,
            "longitude": 129.039653
        },
        {
            "latitude": 35.262772,
            "longitude": 129.039789
        },
        {
            "latitude": 35.26278,
            "longitude": 129.040038
        },
        {
            "latitude": 35.262856,
            "longitude": 129.04029
        },
        {
            "latitude": 35.262903,
            "longitude": 129.040455
        },
        {
            "latitude": 35.262967,
            "longitude": 129.040579
        },
        {
            "latitude": 35.263056,
            "longitude": 129.040673
        },
        {
            "latitude": 35.263102,
            "longitude": 129.040786
        },
        {
            "latitude": 35.263147,
            "longitude": 129.040894
        },
        {
            "latitude": 35.263185,
            "longitude": 129.041012
        },
        {
            "latitude": 35.263211,
            "longitude": 129.041137
        },
        {
            "latitude": 35.263246,
            "longitude": 129.041321
        },
        {
            "latitude": 35.26327,
            "longitude": 129.041473
        },
        {
            "latitude": 35.263306,
            "longitude": 129.041623
        },
        {
            "latitude": 35.263376,
            "longitude": 129.041716
        },
        {
            "latitude": 35.263521,
            "longitude": 129.041814
        },
        {
            "latitude": 35.2637,
            "longitude": 129.042014
        },
        {
            "latitude": 35.263788,
            "longitude": 129.042045
        },
        {
            "latitude": 35.263867,
            "longitude": 129.042116
        },
        {
            "latitude": 35.264103,
            "longitude": 129.042179
        },
        {
            "latitude": 35.26419,
            "longitude": 129.042196
        },
        {
            "latitude": 35.264361,
            "longitude": 129.042243
        },
        {
            "latitude": 35.264449,
            "longitude": 129.042289
        },
        {
            "latitude": 35.264587,
            "longitude": 129.042283
        },
        {
            "latitude": 35.264722,
            "longitude": 129.042287
        },
        {
            "latitude": 35.264759,
            "longitude": 129.042273
        },
        {
            "latitude": 35.264778,
            "longitude": 129.042308
        },
        {
            "latitude": 35.264869,
            "longitude": 129.042306
        },
        {
            "latitude": 35.264978,
            "longitude": 129.042283
        },
        {
            "latitude": 35.265235,
            "longitude": 129.042353
        },
        {
            "latitude": 35.265353,
            "longitude": 129.042394
        },
        {
            "latitude": 35.265448,
            "longitude": 129.042419
        },
        {
            "latitude": 35.265549,
            "longitude": 129.042452
        },
        {
            "latitude": 35.265657,
            "longitude": 129.042525
        },
        {
            "latitude": 35.26585,
            "longitude": 129.042505
        },
        {
            "latitude": 35.26594,
            "longitude": 129.042457
        },
        {
            "latitude": 35.266028,
            "longitude": 129.042409
        },
        {
            "latitude": 35.266181,
            "longitude": 129.042391
        },
        {
            "latitude": 35.26627,
            "longitude": 129.042348
        },
        {
            "latitude": 35.266374,
            "longitude": 129.042336
        },
        {
            "latitude": 35.266486,
            "longitude": 129.042359
        },
        {
            "latitude": 35.266607,
            "longitude": 129.042371
        },
        {
            "latitude": 35.266731,
            "longitude": 129.042407
        },
        {
            "latitude": 35.266839,
            "longitude": 129.042449
        },
        {
            "latitude": 35.266941,
            "longitude": 129.042504
        },
        {
            "latitude": 35.267066,
            "longitude": 129.042546
        },
        {
            "latitude": 35.267198,
            "longitude": 129.042575
        },
        {
            "latitude": 35.267327,
            "longitude": 129.042582
        },
        {
            "latitude": 35.267431,
            "longitude": 129.042595
        },
        {
            "latitude": 35.267522,
            "longitude": 129.042568
        },
        {
            "latitude": 35.267633,
            "longitude": 129.042565
        },
        {
            "latitude": 35.267745,
            "longitude": 129.042595
        },
        {
            "latitude": 35.267836,
            "longitude": 129.042537
        },
        {
            "latitude": 35.267922,
            "longitude": 129.042593
        },
        {
            "latitude": 35.268018,
            "longitude": 129.042577
        },
        {
            "latitude": 35.268118,
            "longitude": 129.042539
        },
        {
            "latitude": 35.268196,
            "longitude": 129.042588
        },
        {
            "latitude": 35.26827,
            "longitude": 129.042618
        },
        {
            "latitude": 35.268349,
            "longitude": 129.042648
        },
        {
            "latitude": 35.268412,
            "longitude": 129.042715
        },
        {
            "latitude": 35.26852,
            "longitude": 129.042669
        },
        {
            "latitude": 35.268608,
            "longitude": 129.042709
        },
        {
            "latitude": 35.268781,
            "longitude": 129.042882
        },
        {
            "latitude": 35.268831,
            "longitude": 129.04298
        },
        {
            "latitude": 35.268916,
            "longitude": 129.043119
        },
        {
            "latitude": 35.268978,
            "longitude": 129.043182
        },
        {
            "latitude": 35.269005,
            "longitude": 129.043229
        },
        {
            "latitude": 35.269099,
            "longitude": 129.043246
        },
        {
            "latitude": 35.269199,
            "longitude": 129.043303
        },
        {
            "latitude": 35.269333,
            "longitude": 129.04334
        },
        {
            "latitude": 35.269438,
            "longitude": 129.043354
        },
        {
            "latitude": 35.269557,
            "longitude": 129.043369
        },
        {
            "latitude": 35.269687,
            "longitude": 129.043388
        },
        {
            "latitude": 35.269774,
            "longitude": 129.043476
        },
        {
            "latitude": 35.269832,
            "longitude": 129.043582
        },
        {
            "latitude": 35.269916,
            "longitude": 129.043744
        },
        {
            "latitude": 35.269977,
            "longitude": 129.043852
        },
        {
            "latitude": 35.270089,
            "longitude": 129.043941
        },
        {
            "latitude": 35.2701,
            "longitude": 129.043943
        },
        {
            "latitude": 35.270175,
            "longitude": 129.044045
        },
        {
            "latitude": 35.270245,
            "longitude": 129.04416
        },
        {
            "latitude": 35.270321,
            "longitude": 129.044251
        },
        {
            "latitude": 35.270437,
            "longitude": 129.044322
        },
        {
            "latitude": 35.270532,
            "longitude": 129.044378
        },
        {
            "latitude": 35.270679,
            "longitude": 129.044542
        },
        {
            "latitude": 35.270774,
            "longitude": 129.044656
        },
        {
            "latitude": 35.270836,
            "longitude": 129.04477
        },
        {
            "latitude": 35.270885,
            "longitude": 129.044879
        },
        {
            "latitude": 35.270953,
            "longitude": 129.044979
        },
        {
            "latitude": 35.270997,
            "longitude": 129.045073
        },
        {
            "latitude": 35.271044,
            "longitude": 129.045205
        },
        {
            "latitude": 35.271117,
            "longitude": 129.045322
        },
        {
            "latitude": 35.271155,
            "longitude": 129.045435
        },
        {
            "latitude": 35.271177,
            "longitude": 129.045538
        },
        {
            "latitude": 35.271227,
            "longitude": 129.045646
        },
        {
            "latitude": 35.271265,
            "longitude": 129.045807
        },
        {
            "latitude": 35.271301,
            "longitude": 129.045911
        },
        {
            "latitude": 35.271389,
            "longitude": 129.045959
        },
        {
            "latitude": 35.271535,
            "longitude": 129.046036
        },
        {
            "latitude": 35.271628,
            "longitude": 129.046057
        },
        {
            "latitude": 35.271747,
            "longitude": 129.046195
        },
        {
            "latitude": 35.271883,
            "longitude": 129.046293
        },
        {
            "latitude": 35.271974,
            "longitude": 129.046368
        },
        {
            "latitude": 35.272088,
            "longitude": 129.046376
        },
        {
            "latitude": 35.272176,
            "longitude": 129.046404
        },
        {
            "latitude": 35.272259,
            "longitude": 129.046377
        },
        {
            "latitude": 35.272377,
            "longitude": 129.046359
        },
        {
            "latitude": 35.272483,
            "longitude": 129.046371
        },
        {
            "latitude": 35.272578,
            "longitude": 129.046341
        },
        {
            "latitude": 35.272732,
            "longitude": 129.046307
        },
        {
            "latitude": 35.272874,
            "longitude": 129.046401
        },
        {
            "latitude": 35.272971,
            "longitude": 129.046377
        },
        {
            "latitude": 35.273046,
            "longitude": 129.04644
        },
        {
            "latitude": 35.273144,
            "longitude": 129.046476
        },
        {
            "latitude": 35.273235,
            "longitude": 129.04656
        },
        {
            "latitude": 35.273331,
            "longitude": 129.046668
        },
        {
            "latitude": 35.27349,
            "longitude": 129.046784
        },
        {
            "latitude": 35.273605,
            "longitude": 129.046849
        },
        {
            "latitude": 35.273692,
            "longitude": 129.046861
        },
        {
            "latitude": 35.273784,
            "longitude": 129.046882
        },
        {
            "latitude": 35.273867,
            "longitude": 129.046955
        },
        {
            "latitude": 35.273937,
            "longitude": 129.047069
        },
        {
            "latitude": 35.27401,
            "longitude": 129.047145
        },
        {
            "latitude": 35.274099,
            "longitude": 129.047166
        },
        {
            "latitude": 35.27416,
            "longitude": 129.047256
        },
        {
            "latitude": 35.274288,
            "longitude": 129.047326
        },
        {
            "latitude": 35.274341,
            "longitude": 129.047479
        },
        {
            "latitude": 35.274361,
            "longitude": 129.047589
        },
        {
            "latitude": 35.274438,
            "longitude": 129.047722
        },
        {
            "latitude": 35.274478,
            "longitude": 129.047815
        },
        {
            "latitude": 35.274541,
            "longitude": 129.047948
        },
        {
            "latitude": 35.274639,
            "longitude": 129.048058
        },
        {
            "latitude": 35.274662,
            "longitude": 129.048186
        },
        {
            "latitude": 35.274688,
            "longitude": 129.048155
        },
        {
            "latitude": 35.274799,
            "longitude": 129.048176
        },
        {
            "latitude": 35.274884,
            "longitude": 129.048237
        },
        {
            "latitude": 35.275012,
            "longitude": 129.048294
        },
        {
            "latitude": 35.275119,
            "longitude": 129.048292
        },
        {
            "latitude": 35.275363,
            "longitude": 129.048331
        },
        {
            "latitude": 35.275545,
            "longitude": 129.048334
        },
        {
            "latitude": 35.275649,
            "longitude": 129.048322
        },
        {
            "latitude": 35.27576,
            "longitude": 129.048281
        },
        {
            "latitude": 35.275877,
            "longitude": 129.048176
        },
        {
            "latitude": 35.276022,
            "longitude": 129.048082
        },
        {
            "latitude": 35.276106,
            "longitude": 129.048018
        },
        {
            "latitude": 35.276266,
            "longitude": 129.04802
        },
        {
            "latitude": 35.276344,
            "longitude": 129.048075
        },
        {
            "latitude": 35.276347,
            "longitude": 129.048081
        },
        {
            "latitude": 35.276465,
            "longitude": 129.048127
        },
        {
            "latitude": 35.276562,
            "longitude": 129.0482
        },
        {
            "latitude": 35.276721,
            "longitude": 129.048253
        },
        {
            "latitude": 35.276816,
            "longitude": 129.048297
        },
        {
            "latitude": 35.276993,
            "longitude": 129.048436
        },
        {
            "latitude": 35.27694,
            "longitude": 129.048501
        },
        {
            "latitude": 35.276835,
            "longitude": 129.048499
        },
        {
            "latitude": 35.276737,
            "longitude": 129.048535
        },
        {
            "latitude": 35.276606,
            "longitude": 129.048635
        },
        {
            "latitude": 35.276517,
            "longitude": 129.048656
        },
        {
            "latitude": 35.276412,
            "longitude": 129.048748
        },
        {
            "latitude": 35.276305,
            "longitude": 129.048855
        },
        {
            "latitude": 35.276213,
            "longitude": 129.048932
        },
        {
            "latitude": 35.276075,
            "longitude": 129.049058
        },
        {
            "latitude": 35.275908,
            "longitude": 129.049144
        },
        {
            "latitude": 35.275775,
            "longitude": 129.049182
        },
        {
            "latitude": 35.27566,
            "longitude": 129.049178
        },
        {
            "latitude": 35.27551,
            "longitude": 129.049188
        },
        {
            "latitude": 35.275401,
            "longitude": 129.0492
        },
        {
            "latitude": 35.2753,
            "longitude": 129.049232
        },
        {
            "latitude": 35.275163,
            "longitude": 129.04934
        },
        {
            "latitude": 35.275091,
            "longitude": 129.049443
        },
        {
            "latitude": 35.275009,
            "longitude": 129.04949
        },
        {
            "latitude": 35.274942,
            "longitude": 129.049527
        },
        {
            "latitude": 35.274891,
            "longitude": 129.049547
        },
        {
            "latitude": 35.274799,
            "longitude": 129.049557
        },
        {
            "latitude": 35.274664,
            "longitude": 129.049628
        },
        {
            "latitude": 35.274602,
            "longitude": 129.049793
        },
        {
            "latitude": 35.274493,
            "longitude": 129.049799
        },
        {
            "latitude": 35.274347,
            "longitude": 129.049898
        },
        {
            "latitude": 35.274264,
            "longitude": 129.049906
        },
        {
            "latitude": 35.274201,
            "longitude": 129.049866
        },
        {
            "latitude": 35.274135,
            "longitude": 129.049984
        },
        {
            "latitude": 35.274094,
            "longitude": 129.050053
        },
        {
            "latitude": 35.273998,
            "longitude": 129.050037
        },
        {
            "latitude": 35.273965,
            "longitude": 129.049921
        },
        {
            "latitude": 35.273937,
            "longitude": 129.049792
        },
        {
            "latitude": 35.273847,
            "longitude": 129.049637
        },
        {
            "latitude": 35.273842,
            "longitude": 129.049561
        },
        {
            "latitude": 35.273722,
            "longitude": 129.049596
        },
        {
            "latitude": 35.273678,
            "longitude": 129.049693
        },
        {
            "latitude": 35.273593,
            "longitude": 129.049821
        },
        {
            "latitude": 35.273533,
            "longitude": 129.049925
        },
        {
            "latitude": 35.273469,
            "longitude": 129.050029
        },
        {
            "latitude": 35.273366,
            "longitude": 129.050068
        },
        {
            "latitude": 35.273307,
            "longitude": 129.050157
        },
        {
            "latitude": 35.273216,
            "longitude": 129.050149
        },
        {
            "latitude": 35.273137,
            "longitude": 129.050134
        },
        {
            "latitude": 35.273083,
            "longitude": 129.050228
        },
        {
            "latitude": 35.273029,
            "longitude": 129.050352
        },
        {
            "latitude": 35.273107,
            "longitude": 129.050459
        },
        {
            "latitude": 35.273057,
            "longitude": 129.050578
        },
        {
            "latitude": 35.273021,
            "longitude": 129.050703
        },
        {
            "latitude": 35.272924,
            "longitude": 129.050847
        },
        {
            "latitude": 35.272851,
            "longitude": 129.050901
        },
        {
            "latitude": 35.272711,
            "longitude": 129.051124
        },
        {
            "latitude": 35.27265,
            "longitude": 129.051223
        },
        {
            "latitude": 35.272597,
            "longitude": 129.051319
        },
        {
            "latitude": 35.272525,
            "longitude": 129.051365
        },
        {
            "latitude": 35.272468,
            "longitude": 129.051448
        },
        {
            "latitude": 35.272377,
            "longitude": 129.051542
        },
        {
            "latitude": 35.272296,
            "longitude": 129.051614
        },
        {
            "latitude": 35.2723,
            "longitude": 129.051739
        },
        {
            "latitude": 35.272292,
            "longitude": 129.051868
        },
        {
            "latitude": 35.272336,
            "longitude": 129.052011
        },
        {
            "latitude": 35.27238,
            "longitude": 129.052145
        },
        {
            "latitude": 35.272305,
            "longitude": 129.052237
        },
        {
            "latitude": 35.272229,
            "longitude": 129.052306
        },
        {
            "latitude": 35.272108,
            "longitude": 129.052396
        },
        {
            "latitude": 35.271966,
            "longitude": 129.052528
        },
        {
            "latitude": 35.271891,
            "longitude": 129.052652
        },
        {
            "latitude": 35.271841,
            "longitude": 129.052812
        },
        {
            "latitude": 35.271763,
            "longitude": 129.052884
        },
        {
            "latitude": 35.271625,
            "longitude": 129.052889
        },
        {
            "latitude": 35.271521,
            "longitude": 129.052961
        },
        {
            "latitude": 35.271457,
            "longitude": 129.053046
        },
        {
            "latitude": 35.271352,
            "longitude": 129.053156
        },
        {
            "latitude": 35.271146,
            "longitude": 129.05319
        },
        {
            "latitude": 35.271076,
            "longitude": 129.053128
        },
        {
            "latitude": 35.270963,
            "longitude": 129.053013
        },
        {
            "latitude": 35.270848,
            "longitude": 129.052936
        },
        {
            "latitude": 35.270677,
            "longitude": 129.052874
        },
        {
            "latitude": 35.270489,
            "longitude": 129.052808
        },
        {
            "latitude": 35.270296,
            "longitude": 129.052781
        },
        {
            "latitude": 35.270214,
            "longitude": 129.052698
        },
        {
            "latitude": 35.270134,
            "longitude": 129.052624
        },
        {
            "latitude": 35.269902,
            "longitude": 129.052449
        },
        {
            "latitude": 35.269817,
            "longitude": 129.052319
        },
        {
            "latitude": 35.269799,
            "longitude": 129.052181
        },
        {
            "latitude": 35.269706,
            "longitude": 129.05216
        },
        {
            "latitude": 35.269586,
            "longitude": 129.052078
        },
        {
            "latitude": 35.26948,
            "longitude": 129.05203
        },
        {
            "latitude": 35.26939,
            "longitude": 129.051934
        },
        {
            "latitude": 35.269285,
            "longitude": 129.051811
        },
        {
            "latitude": 35.269176,
            "longitude": 129.051724
        },
        {
            "latitude": 35.269048,
            "longitude": 129.05172
        },
        {
            "latitude": 35.268965,
            "longitude": 129.051686
        },
        {
            "latitude": 35.268858,
            "longitude": 129.051631
        },
        {
            "latitude": 35.268716,
            "longitude": 129.051528
        },
        {
            "latitude": 35.268582,
            "longitude": 129.051462
        },
        {
            "latitude": 35.2685,
            "longitude": 129.051377
        },
        {
            "latitude": 35.26835,
            "longitude": 129.051336
        },
        {
            "latitude": 35.268108,
            "longitude": 129.051388
        },
        {
            "latitude": 35.267969,
            "longitude": 129.051353
        },
        {
            "latitude": 35.267841,
            "longitude": 129.051309
        },
        {
            "latitude": 35.267731,
            "longitude": 129.051253
        },
        {
            "latitude": 35.267691,
            "longitude": 129.051269
        },
        {
            "latitude": 35.267636,
            "longitude": 129.051431
        },
        {
            "latitude": 35.267622,
            "longitude": 129.051555
        },
        {
            "latitude": 35.267604,
            "longitude": 129.051685
        },
        {
            "latitude": 35.267432,
            "longitude": 129.051691
        },
        {
            "latitude": 35.267285,
            "longitude": 129.051788
        },
        {
            "latitude": 35.2672,
            "longitude": 129.051872
        },
        {
            "latitude": 35.267146,
            "longitude": 129.051972
        },
        {
            "latitude": 35.267024,
            "longitude": 129.051936
        },
        {
            "latitude": 35.266935,
            "longitude": 129.051895
        },
        {
            "latitude": 35.266644,
            "longitude": 129.051556
        },
        {
            "latitude": 35.266399,
            "longitude": 129.051222
        },
        {
            "latitude": 35.266237,
            "longitude": 129.051128
        },
        {
            "latitude": 35.266168,
            "longitude": 129.051035
        },
        {
            "latitude": 35.266089,
            "longitude": 129.050977
        },
        {
            "latitude": 35.266013,
            "longitude": 129.050864
        },
        {
            "latitude": 35.265917,
            "longitude": 129.050824
        },
        {
            "latitude": 35.265715,
            "longitude": 129.050704
        },
        {
            "latitude": 35.265622,
            "longitude": 129.05062
        },
        {
            "latitude": 35.265514,
            "longitude": 129.050595
        },
        {
            "latitude": 35.265379,
            "longitude": 129.050607
        },
        {
            "latitude": 35.265186,
            "longitude": 129.050639
        },
        {
            "latitude": 35.265115,
            "longitude": 129.050787
        },
        {
            "latitude": 35.265028,
            "longitude": 129.050806
        },
        {
            "latitude": 35.264897,
            "longitude": 129.050691
        },
        {
            "latitude": 35.264753,
            "longitude": 129.050626
        },
        {
            "latitude": 35.264601,
            "longitude": 129.050534
        },
        {
            "latitude": 35.264506,
            "longitude": 129.050473
        },
        {
            "latitude": 35.264472,
            "longitude": 129.050357
        },
        {
            "latitude": 35.264441,
            "longitude": 129.050199
        },
        {
            "latitude": 35.264391,
            "longitude": 129.050042
        },
        {
            "latitude": 35.264293,
            "longitude": 129.049978
        },
        {
            "latitude": 35.2642,
            "longitude": 129.049941
        },
        {
            "latitude": 35.264128,
            "longitude": 129.049817
        },
        {
            "latitude": 35.264068,
            "longitude": 129.049733
        },
        {
            "latitude": 35.263927,
            "longitude": 129.049732
        },
        {
            "latitude": 35.263814,
            "longitude": 129.049754
        },
        {
            "latitude": 35.263658,
            "longitude": 129.049775
        },
        {
            "latitude": 35.263499,
            "longitude": 129.049815
        },
        {
            "latitude": 35.263367,
            "longitude": 129.04978
        },
        {
            "latitude": 35.263299,
            "longitude": 129.049821
        },
        {
            "latitude": 35.263313,
            "longitude": 129.049818
        },
        {
            "latitude": 35.263229,
            "longitude": 129.049839
        },
        {
            "latitude": 35.263139,
            "longitude": 129.049849
        },
        {
            "latitude": 35.263043,
            "longitude": 129.049908
        },
        {
            "latitude": 35.262932,
            "longitude": 129.049934
        },
        {
            "latitude": 35.262832,
            "longitude": 129.04991
        },
        {
            "latitude": 35.262771,
            "longitude": 129.049859
        },
        {
            "latitude": 35.262654,
            "longitude": 129.04988
        },
        {
            "latitude": 35.262498,
            "longitude": 129.049877
        },
        {
            "latitude": 35.262354,
            "longitude": 129.049836
        },
        {
            "latitude": 35.262234,
            "longitude": 129.04984
        },
        {
            "latitude": 35.262135,
            "longitude": 129.049801
        },
        {
            "latitude": 35.261995,
            "longitude": 129.04974
        },
        {
            "latitude": 35.261892,
            "longitude": 129.049699
        },
        {
            "latitude": 35.261741,
            "longitude": 129.049684
        },
        {
            "latitude": 35.261635,
            "longitude": 129.049635
        },
        {
            "latitude": 35.261498,
            "longitude": 129.049563
        },
        {
            "latitude": 35.26134,
            "longitude": 129.049545
        },
        {
            "latitude": 35.261233,
            "longitude": 129.049621
        },
        {
            "latitude": 35.261138,
            "longitude": 129.049682
        },
        {
            "latitude": 35.261035,
            "longitude": 129.049705
        },
        {
            "latitude": 35.260936,
            "longitude": 129.049749
        },
        {
            "latitude": 35.26088,
            "longitude": 129.04976
        },
        {
            "latitude": 35.26077,
            "longitude": 129.049815
        },
        {
            "latitude": 35.260694,
            "longitude": 129.049871
        },
        {
            "latitude": 35.260399,
            "longitude": 129.049907
        },
        {
            "latitude": 35.260235,
            "longitude": 129.049941
        },
        {
            "latitude": 35.260148,
            "longitude": 129.049991
        },
        {
            "latitude": 35.260036,
            "longitude": 129.050034
        },
        {
            "latitude": 35.259905,
            "longitude": 129.050025
        },
        {
            "latitude": 35.25979,
            "longitude": 129.050001
        },
        {
            "latitude": 35.259672,
            "longitude": 129.050052
        },
        {
            "latitude": 35.25962,
            "longitude": 129.050148
        },
        {
            "latitude": 35.259534,
            "longitude": 129.050245
        },
        {
            "latitude": 35.259411,
            "longitude": 129.050215
        },
        {
            "latitude": 35.259325,
            "longitude": 129.050186
        },
        {
            "latitude": 35.259325,
            "longitude": 129.050186
        },
        {
            "latitude": 35.258964,
            "longitude": 129.051234
        },
        {
            "latitude": 35.258853,
            "longitude": 129.05128
        },
        {
            "latitude": 35.258734,
            "longitude": 129.051288
        },
        {
            "latitude": 35.258596,
            "longitude": 129.051237
        },
        {
            "latitude": 35.258506,
            "longitude": 129.051216
        },
        {
            "latitude": 35.258506,
            "longitude": 129.051216
        },
        {
            "latitude": 35.25088,
            "longitude": 129.055779
        },
        {
            "latitude": 35.25088,
            "longitude": 129.055779
        },
        {
            "latitude": 35.23567,
            "longitude": 129.013832
        },
        {
            "latitude": 35.235574,
            "longitude": 129.013837
        },
        {
            "latitude": 35.23558,
            "longitude": 129.013692
        },
        {
            "latitude": 35.235625,
            "longitude": 129.013571
        },
        {
            "latitude": 35.235625,
            "longitude": 129.013571
        },
        {
            "latitude": 35.235625,
            "longitude": 129.013571
        }
    ],
    "total_distance": 12910.968829754846,
    "surface_distances": {},
    "surface_ratios": {}
}